mcp_security_framework/__init__.py
mcp_security_framework/constants.py
mcp_security_framework/cli/__init__.py
mcp_security_framework/cli/cert_cli.py
mcp_security_framework/cli/security_cli.py
mcp_security_framework/core/__init__.py
mcp_security_framework/core/adapter_wrapper.py
mcp_security_framework/core/audit_logger.py
mcp_security_framework/core/auth_manager.py
mcp_security_framework/core/cert_manager.py
mcp_security_framework/core/permission_manager.py
mcp_security_framework/core/rate_limiter.py
mcp_security_framework/core/security_adapter.py
mcp_security_framework/core/security_manager.py
mcp_security_framework/core/ssl_manager.py
mcp_security_framework/examples/__init__.py
mcp_security_framework/examples/comprehensive_example.py
mcp_security_framework/examples/django_example.py
mcp_security_framework/examples/fastapi_example.py
mcp_security_framework/examples/flask_example.py
mcp_security_framework/examples/gateway_example.py
mcp_security_framework/examples/microservice_example.py
mcp_security_framework/examples/standalone_example.py
mcp_security_framework/examples/test_all_examples.py
mcp_security_framework/middleware/__init__.py
mcp_security_framework/middleware/auth_middleware.py
mcp_security_framework/middleware/fastapi_auth_middleware.py
mcp_security_framework/middleware/fastapi_middleware.py
mcp_security_framework/middleware/flask_auth_middleware.py
mcp_security_framework/middleware/flask_middleware.py
mcp_security_framework/middleware/mtls_middleware.py
mcp_security_framework/middleware/rate_limit_middleware.py
mcp_security_framework/middleware/security_middleware.py
mcp_security_framework/schemas/__init__.py
mcp_security_framework/schemas/config.py
mcp_security_framework/schemas/models.py
mcp_security_framework/schemas/operation_context.py
mcp_security_framework/schemas/responses.py
mcp_security_framework/tests/__init__.py
mcp_security_framework/utils/__init__.py
mcp_security_framework/utils/cert_utils.py
mcp_security_framework/utils/crypto_utils.py
mcp_security_framework-1.6.0.dist-info/METADATA
mcp_security_framework-1.6.0.dist-info/WHEEL
mcp_security_framework-1.6.0.dist-info/entry_points.txt
mcp_security_framework-1.6.0.dist-info/top_level.txt
mcp_security_framework-1.6.0.dist-info/RECORD
