Metadata-Version: 2.4
Name: mcp-security-framework
Version: 1.6.0
Summary: Universal security framework for microservices with SSL/TLS, authentication, authorization, and rate limiting. Added extensible security adapter system for custom operation validation, structured audit logging, and operation context support. Comprehensive test coverage with 1104+ tests. Fully backward compatible. Requires cryptography>=42.0.0 for certificate operations.
Author-email: Vasiliy Zdanovskiy <vasilyvz@gmail.com>
Maintainer-email: Vasiliy Zdanovskiy <vasilyvz@gmail.com>
License: MIT
Project-URL: Homepage, https://github.com/maverikod/mcp-security-framework
Project-URL: Documentation, https://mcp-security-framework.readthedocs.io/
Project-URL: Repository, https://github.com/maverikod/mcp-security-framework
Project-URL: Bug Tracker, https://github.com/maverikod/mcp-security-framework/issues
Project-URL: Security Policy, https://github.com/maverikod/mcp-security-framework/security/policy
Keywords: security,authentication,authorization,ssl,tls,microservices,fastapi,flask,adapters,audit,logging
Classifier: Development Status :: 3 - Alpha
Classifier: Intended Audience :: Developers
Classifier: License :: OSI Approved :: MIT License
Classifier: Operating System :: OS Independent
Classifier: Programming Language :: Python :: 3
Classifier: Programming Language :: Python :: 3.8
Classifier: Programming Language :: Python :: 3.9
Classifier: Programming Language :: Python :: 3.10
Classifier: Programming Language :: Python :: 3.11
Classifier: Programming Language :: Python :: 3.12
Classifier: Topic :: Security
Classifier: Topic :: Software Development :: Libraries :: Python Modules
Classifier: Topic :: System :: Systems Administration :: Authentication/Directory
Requires-Python: >=3.8
Requires-Dist: cryptography>=42.0.0
Requires-Dist: pydantic<3.0.0,>=1.8.0
Requires-Dist: PyJWT>=2.0.0
Requires-Dist: click>=8.0.0
Requires-Dist: typing-extensions>=4.0.0
Requires-Dist: packaging>=20.0
Provides-Extra: fastapi
Requires-Dist: fastapi>=0.68.0; extra == "fastapi"
Requires-Dist: uvicorn[standard]>=0.15.0; extra == "fastapi"
Provides-Extra: flask
Requires-Dist: flask>=2.0.0; extra == "flask"
Requires-Dist: werkzeug>=2.0.0; extra == "flask"
Provides-Extra: django
Requires-Dist: django>=3.2.0; extra == "django"
Provides-Extra: dev
Requires-Dist: pytest>=7.0.0; extra == "dev"
Requires-Dist: pytest-cov>=4.0.0; extra == "dev"
Requires-Dist: pytest-asyncio>=0.21.0; extra == "dev"
Requires-Dist: black>=22.0.0; extra == "dev"
Requires-Dist: isort>=5.10.0; extra == "dev"
Requires-Dist: flake8>=5.0.0; extra == "dev"
Requires-Dist: mypy>=1.0.0; extra == "dev"
Requires-Dist: pre-commit>=2.20.0; extra == "dev"
Requires-Dist: tox>=4.0.0; extra == "dev"
Provides-Extra: docs
Requires-Dist: sphinx>=5.0.0; extra == "docs"
Requires-Dist: sphinx-rtd-theme>=1.0.0; extra == "docs"
Requires-Dist: myst-parser>=0.18.0; extra == "docs"
Provides-Extra: test
Requires-Dist: pytest>=7.0.0; extra == "test"
Requires-Dist: pytest-cov>=4.0.0; extra == "test"
Requires-Dist: pytest-asyncio>=0.21.0; extra == "test"
Requires-Dist: pytest-mock>=3.8.0; extra == "test"
Requires-Dist: httpx>=0.24.0; extra == "test"
